arcade/VERSION
arcade/__init__.py
arcade/__main__.py
arcade/application.py
arcade/clock.py
arcade/context.py
arcade/controller.py
arcade/earclip.py
arcade/easing.py
arcade/exceptions.py
arcade/geometry.py
arcade/isometric.py
arcade/joysticks.py
arcade/math.py
arcade/paths.py
arcade/perf_graph.py
arcade/perf_info.py
arcade/physics_engines.py
arcade/py.typed
arcade/pymunk_physics_engine.py
arcade/scene.py
arcade/screenshot.py
arcade/sections.py
arcade/shape_list.py
arcade/sound.py
arcade/start_finish_data.py
arcade/text.py
arcade/uicolor.py
arcade/utils.py
arcade/version.py
arcade/window_commands.py
arcade/__pyinstaller/__init__.py
arcade/__pyinstaller/hook-arcade.py
arcade/cache/__init__.py
arcade/cache/hit_box.py
arcade/cache/image_data.py
arcade/cache/texture.py
arcade/camera/__init__.py
arcade/camera/camera_2d.py
arcade/camera/data_types.py
arcade/camera/default.py
arcade/camera/orthographic.py
arcade/camera/perspective.py
arcade/camera/projection_functions.py
arcade/camera/static.py
arcade/camera/grips/__init__.py
arcade/camera/grips/constrain.py
arcade/camera/grips/position.py
arcade/camera/grips/rotate.py
arcade/camera/grips/screen_shake_2d.py
arcade/camera/grips/strafe.py
arcade/color/__init__.py
arcade/csscolor/__init__.py
arcade/draw/__init__.py
arcade/draw/arc.py
arcade/draw/circle.py
arcade/draw/helpers.py
arcade/draw/line.py
arcade/draw/parabola.py
arcade/draw/point.py
arcade/draw/polygon.py
arcade/draw/rect.py
arcade/draw/triangle.py
arcade/examples/__init__.py
arcade/examples/array_backed_grid.py
arcade/examples/array_backed_grid_buffered.py
arcade/examples/array_backed_grid_sprites_1.py
arcade/examples/array_backed_grid_sprites_2.py
arcade/examples/astar_pathfinding.py
arcade/examples/asteroid_smasher.py
arcade/examples/background_blending.py
arcade/examples/background_groups.py
arcade/examples/background_parallax.py
arcade/examples/background_scrolling.py
arcade/examples/background_stationary.py
arcade/examples/bouncing_rectangle.py
arcade-3.3.1.dist-info/METADATA
arcade-3.3.1.dist-info/WHEEL
arcade-3.3.1.dist-info/entry_points.txt
arcade-3.3.1.dist-info/top_level.txt
arcade-3.3.1.dist-info/RECORD
