Metadata-Version: 2.4
Name: arcade
Version: 3.3.1
Summary: Arcade Game Development Library
Author-email: Paul Vincent Craven <paul@cravenfamily.com>
License: License
Project-URL: Homepage, https://api.arcade.academy
Project-URL: Documentation, https://api.arcade.academy/
Project-URL: Examples, https://api.arcade.academy/en/latest/examples/index.html
Project-URL: Issues, https://github.com/pythonarcade/arcade/issues
Project-URL: Source, https://github.com/pythonarcade/arcade
Project-URL: Book, https://learn.arcade.academy
Classifier: Development Status :: 5 - Production/Stable
Classifier: Intended Audience :: Developers
Classifier: License :: OSI Approved :: MIT License
Classifier: Operating System :: OS Independent
Classifier: Programming Language :: Python
Classifier: Programming Language :: Python :: 3.10
Classifier: Programming Language :: Python :: 3.11
Classifier: Programming Language :: Python :: 3.12
Classifier: Programming Language :: Python :: 3.13
Classifier: Programming Language :: Python :: Implementation :: CPython
Classifier: Topic :: Software Development :: Libraries :: Python Modules
Requires-Python: >=3.10
Requires-Dist: pyglet~=2.1.5
Requires-Dist: pillow~=11.0.0
Requires-Dist: pymunk~=6.9.0
Requires-Dist: pytiled-parser~=2.2.9
Provides-Extra: dev
Requires-Dist: sphinx==8.1.3; extra == "dev"
Requires-Dist: sphinx_rtd_theme==3.0.2; extra == "dev"
Requires-Dist: sphinx-rtd-dark-mode==1.3.0; extra == "dev"
Requires-Dist: sphinx-autobuild==2024.10.3; extra == "dev"
Requires-Dist: sphinx-copybutton==0.5.2; extra == "dev"
Requires-Dist: sphinx-sitemap==2.6.0; extra == "dev"
Requires-Dist: sphinx-togglebutton==0.3.2; extra == "dev"
Requires-Dist: pygments==2.19.1; extra == "dev"
Requires-Dist: docutils==0.21.2; extra == "dev"
Requires-Dist: pytest; extra == "dev"
Requires-Dist: pytest-cov; extra == "dev"
Requires-Dist: pytest-mock; extra == "dev"
Requires-Dist: coverage; extra == "dev"
Requires-Dist: coveralls; extra == "dev"
Requires-Dist: ruff; extra == "dev"
Requires-Dist: mypy; extra == "dev"
Requires-Dist: pyright==1.1.387; extra == "dev"
Requires-Dist: typer[all]==0.12.5; extra == "dev"
Requires-Dist: wheel; extra == "dev"
Provides-Extra: testing-libraries
Requires-Dist: pytest; extra == "testing-libraries"
Requires-Dist: pytest-mock; extra == "testing-libraries"
Requires-Dist: pytest-cov; extra == "testing-libraries"
Requires-Dist: pyyaml==6.0.1; extra == "testing-libraries"
